scripts_json/__init__.py
scripts_json/main.py
scripts_json-1.0.4.dist-info/entry_points.txt
scripts_json-1.0.4.dist-info/WHEEL
scripts_json-1.0.4.dist-info/METADATA
scripts_json-1.0.4.dist-info/RECORD
